basic_memory_hooks/__init__.py
basic_memory_hooks/__main__.py
basic_memory_hooks/api.py
basic_memory_hooks/config.py
basic_memory_hooks/engine.py
basic_memory_hooks/hook.py
basic_memory_hooks/parser.py
basic_memory_hooks/types.py
basic_memory_hooks/hooks/__init__.py
basic_memory_hooks/hooks/formatting.py
basic_memory_hooks/hooks/validation.py
basic_memory_hooks-0.0.1.dist-info/METADATA
basic_memory_hooks-0.0.1.dist-info/WHEEL
basic_memory_hooks-0.0.1.dist-info/RECORD
