Metadata-Version: 2.4
Name: basic-memory-hooks
Version: 0.0.1
Summary: Structured output for your memos
Project-URL: Homepage, https://github.com/basicmachines-co/basic-memory-hooks
Project-URL: Repository, https://github.com/basicmachines-co/basic-memory-hooks
Author-email: Drew Cain <groksrc@gmail.com>
License: MIT
Classifier: Development Status :: 3 - Alpha
Classifier: Intended Audience :: Developers
Classifier: License :: OSI Approved :: MIT License
Classifier: Programming Language :: Python :: 3
Classifier: Programming Language :: Python :: 3.11
Classifier: Programming Language :: Python :: 3.12
Requires-Python: >=3.11
Requires-Dist: fastapi>=0.104.0
Requires-Dist: pyyaml>=6.0
Requires-Dist: uvicorn>=0.24.0
Provides-Extra: dev
Requires-Dist: httpx>=0.25.0; extra == 'dev'
Requires-Dist: pytest-asyncio>=0.21; extra == 'dev'
Requires-Dist: pytest>=7.0; extra == 'dev'
Requires-Dist: ruff>=0.1.0; extra == 'dev'
